{
  "snapshot_id": "topology_392_t06",
  "topology_id": 392,
  "timestep": 6,
  "queue_model": "mm1",
  "global_features": {
    "time_of_day": 12.0,
    "diurnal_factor": 1.15,
    "flash_event": 0,
    "flash_multiplier": 1.0,
    "traffic_profile": "web",
    "network_load_mbps": 89.77875228144413
  },
  "edge_labels": [
    {
      "edge_id": 0,
      "u": 0,
      "v": 1,
      "bandwidth_mbps": 948.7865659207664,
      "load_mbps": 21.27599008501968,
      "utilization": 0.022424421729002903,
      "queue_length_pkts": 0.0005143895787265458,
      "latency_ms": 2.769905356889417,
      "propagation_delay_ms": 2.7698811798909944,
      "link_reliability": 0.9694689634329403,
      "cost_metric": 3.2968700917910763,
      "is_bottleneck": 0,
      "is_inter_domain": false
    },
    {
      "edge_id": 1,
      "u": 0,
      "v": 3,
      "bandwidth_mbps": 245.73892404576014,
      "load_mbps": 6.241062462005545,
      "utilization": 0.025397126182758776,
      "queue_length_pkts": 0.0006618224054856678,
      "latency_ms": 3.1869197751507703,
      "propagation_delay_ms": 3.186813731923433,
      "link_reliability": 0.9826298318499077,
      "cost_metric": 5.221493430882694,
      "is_bottleneck": 0,
      "is_inter_domain": false
    },
    {
      "edge_id": 2,
      "u": 0,
      "v": 6,
      "bandwidth_mbps": 94.85611532791518,
      "load_mbps": 17.21939713207021,
      "utilization": 0.1815317554650345,
      "queue_length_pkts": 0.04026274502676722,
      "latency_ms": 12.334413656842834,
      "propagation_delay_ms": 12.332075436479021,
      "link_reliability": 0.988133242923956,
      "cost_metric": 17.603216872869417,
      "is_bottleneck": 0,
      "is_inter_domain": true
    },
    {
      "edge_id": 3,
      "u": 0,
      "v": 7,
      "bandwidth_mbps": 47.5754427546498,
      "load_mbps": 5.964291400715334,
      "utilization": 0.1253649163387431,
      "queue_length_pkts": 0.01796905079868366,
      "latency_ms": 11.197670759870922,
      "propagation_delay_ms": 11.194657987759129,
      "link_reliability": 0.9729216821491062,
      "cost_metric": 21.704281672787943,
      "is_bottleneck": 0,
      "is_inter_domain": true
    },
    {
      "edge_id": 4,
      "u": 1,
      "v": 2,
      "bandwidth_mbps": 603.1530284628816,
      "load_mbps": 20.763177555668285,
      "utilization": 0.0344243941020783,
      "queue_length_pkts": 0.0012272875392219497,
      "latency_ms": 3.839453069420337,
      "propagation_delay_ms": 3.8393939605707432,
      "link_reliability": 0.9547578441590578,
      "cost_metric": 4.668370980340065,
      "is_bottleneck": 0,
      "is_inter_domain": false
    },
    {
      "edge_id": 5,
      "u": 2,
      "v": 3,
      "bandwidth_mbps": 121.26520998970715,
      "load_mbps": 5.25641138367441,
      "utilization": 0.04334640895043656,
      "queue_length_pkts": 0.0019640454878103748,
      "latency_ms": 1.4088531169587555,
      "propagation_delay_ms": 1.4084794693607172,
      "link_reliability": 0.9515542714744172,
      "cost_metric": 5.531673582845033,
      "is_bottleneck": 0,
      "is_inter_domain": false
    },
    {
      "edge_id": 6,
      "u": 2,
      "v": 9,
      "bandwidth_mbps": 86.56618754212163,
      "load_mbps": 23.462801412308455,
      "utilization": 0.2710388672354533,
      "queue_length_pkts": 0.10077638470747632,
      "latency_ms": 8.142087307688964,
      "propagation_delay_ms": 8.13779215201098,
      "link_reliability": 0.9973957196871994,
      "cost_metric": 13.913719384069209,
      "is_bottleneck": 0,
      "is_inter_domain": true
    },
    {
      "edge_id": 7,
      "u": 3,
      "v": 8,
      "bandwidth_mbps": 11.257349541051694,
      "load_mbps": 0.0,
      "utilization": 0.0,
      "queue_length_pkts": 1.000001000001e-12,
      "latency_ms": 8.360278591087273,
      "propagation_delay_ms": 8.360278502256328,
      "link_reliability": 0.9735371262666033,
      "cost_metric": 52.77570667890408,
      "is_bottleneck": 0,
      "is_inter_domain": true
    },
    {
      "edge_id": 8,
      "u": 4,
      "v": 5,
      "bandwidth_mbps": 426.9469443065403,
      "load_mbps": 19.03943937777298,
      "utilization": 0.04459439195354213,
      "queue_length_pkts": 0.0020814822280271167,
      "latency_ms": 2.9540134238971847,
      "propagation_delay_ms": 2.953904099132588,
      "link_reliability": 0.9888168247269562,
      "cost_metric": 4.125009798956988,
      "is_bottleneck": 0,
      "is_inter_domain": false
    },
    {
      "edge_id": 9,
      "u": 4,
      "v": 7,
      "bandwidth_mbps": 102.28267797369594,
      "load_mbps": 6.286941733699555,
      "utilization": 0.06146633876086398,
      "queue_length_pkts": 0.0040255463993450055,
      "latency_ms": 4.5611471169612825,
      "propagation_delay_ms": 4.560506814160675,
      "link_reliability": 0.9892901000750596,
      "cost_metric": 9.448920081249607,
      "is_bottleneck": 0,
      "is_inter_domain": false
    },
    {
      "edge_id": 10,
      "u": 4,
      "v": 9,
      "bandwidth_mbps": 80.17600253411067,
      "load_mbps": 25.403454944468113,
      "utilization": 0.31684611531561807,
      "queue_length_pkts": 0.14695292384523137,
      "latency_ms": 12.495259853342326,
      "propagation_delay_ms": 12.489475092010984,
      "link_reliability": 0.9820374503876491,
      "cost_metric": 18.72575507849792,
      "is_bottleneck": 0,
      "is_inter_domain": true
    },
    {
      "edge_id": 11,
      "u": 5,
      "v": 6,
      "bandwidth_mbps": 419.1951634206887,
      "load_mbps": 22.816758767811763,
      "utilization": 0.0544299189466404,
      "queue_length_pkts": 0.0031331533599683126,
      "latency_ms": 1.8141811888390647,
      "propagation_delay_ms": 1.814043870765457,
      "link_reliability": 0.9745184088580033,
      "cost_metric": 3.006805724027153,
      "is_bottleneck": 0,
      "is_inter_domain": false
    },
    {
      "edge_id": 12,
      "u": 6,
      "v": 7,
      "bandwidth_mbps": 303.800616004365,
      "load_mbps": 3.8314292268340204,
      "utilization": 0.012611657202100507,
      "queue_length_pkts": 0.00016108545188268345,
      "latency_ms": 3.2711111218314946,
      "propagation_delay_ms": 3.2710690786558683,
      "link_reliability": 0.9515963827219952,
      "cost_metric": 4.916885359663067,
      "is_bottleneck": 0,
      "is_inter_domain": false
    },
    {
      "edge_id": 13,
      "u": 8,
      "v": 9,
      "bandwidth_mbps": 847.4247069718446,
      "load_mbps": 14.546000204323603,
      "utilization": 0.017164947026741446,
      "queue_length_pkts": 0.0002997811337105989,
      "latency_ms": 2.575983197309589,
      "propagation_delay_ms": 2.57596258812978,
      "link_reliability": 0.9407368954299702,
      "cost_metric": 3.165985508026323,
      "is_bottleneck": 0,
      "is_inter_domain": false
    },
    {
      "edge_id": 14,
      "u": 8,
      "v": 10,
      "bandwidth_mbps": 103.93109528364235,
      "load_mbps": 0.0,
      "utilization": 0.0,
      "queue_length_pkts": 1.000001000001e-12,
      "latency_ms": 5.004955187580012,
      "propagation_delay_ms": 5.004955177958243,
      "link_reliability": 0.9485069109368695,
      "cost_metric": 9.815834911645556,
      "is_bottleneck": 0,
      "is_inter_domain": false
    },
    {
      "edge_id": 15,
      "u": 9,
      "v": 10,
      "bandwidth_mbps": 625.9974888146938,
      "load_mbps": 19.440889376197045,
      "utilization": 0.03105585840768746,
      "queue_length_pkts": 0.0009953786808116491,
      "latency_ms": 4.389561895507813,
      "propagation_delay_ms": 4.389510695243178,
      "link_reliability": 0.9519974678231665,
      "cost_metric": 5.188235944040476,
      "is_bottleneck": 0,
      "is_inter_domain": false
    }
  ],
  "path_labels": [
    {
      "source": 0,
      "target": 1,
      "demand_mbps": 0.5791851283970273,
      "path_hops": 1,
      "e2e_latency_ms": 2.769905356889417,
      "path_bottleneck_count": 0
    },
    {
      "source": 0,
      "target": 2,
      "demand_mbps": 0.8164775575710815,
      "path_hops": 2,
      "e2e_latency_ms": 6.609358426309754,
      "path_bottleneck_count": 0
    },
    {
      "source": 0,
      "target": 3,
      "demand_mbps": 0.15492984609606889,
      "path_hops": 1,
      "e2e_latency_ms": 3.1869197751507703,
      "path_bottleneck_count": 0
    },
    {
      "source": 0,
      "target": 4,
      "demand_mbps": 1.842036094522208,
      "path_hops": 3,
      "e2e_latency_ms": 17.102608269579083,
      "path_bottleneck_count": 0
    },
    {
      "source": 0,
      "target": 5,
      "demand_mbps": 1.2572105492134085,
      "path_hops": 2,
      "e2e_latency_ms": 14.148594845681899,
      "path_bottleneck_count": 0
    },
    {
      "source": 0,
      "target": 6,
      "demand_mbps": 0.5046778456220967,
      "path_hops": 1,
      "e2e_latency_ms": 12.334413656842834,
      "path_bottleneck_count": 0
    },
    {
      "source": 0,
      "target": 7,
      "demand_mbps": 0.533474142601559,
      "path_hops": 1,
      "e2e_latency_ms": 11.197670759870922,
      "path_bottleneck_count": 0
    },
    {
      "source": 0,
      "target": 8,
      "demand_mbps": 0.891936172568033,
      "path_hops": 4,
      "e2e_latency_ms": 17.327428931308308,
      "path_bottleneck_count": 0
    },
    {
      "source": 0,
      "target": 9,
      "demand_mbps": 1.2210782727560043,
      "path_hops": 3,
      "e2e_latency_ms": 14.751445733998718,
      "path_bottleneck_count": 0
    },
    {
      "source": 0,
      "target": 10,
      "demand_mbps": 1.056021487097331,
      "path_hops": 4,
      "e2e_latency_ms": 19.141007629506532,
      "path_bottleneck_count": 0
    },
    {
      "source": 1,
      "target": 0,
      "demand_mbps": 0.3984597882549868,
      "path_hops": 1,
      "e2e_latency_ms": 2.769905356889417,
      "path_bottleneck_count": 0
    },
    {
      "source": 1,
      "target": 2,
      "demand_mbps": 0.8528364508916592,
      "path_hops": 1,
      "e2e_latency_ms": 3.839453069420337,
      "path_bottleneck_count": 0
    },
    {
      "source": 1,
      "target": 3,
      "demand_mbps": 0.4619087977651552,
      "path_hops": 2,
      "e2e_latency_ms": 5.956825132040187,
      "path_bottleneck_count": 0
    },
    {
      "source": 1,
      "target": 4,
      "demand_mbps": 0.30723073585095895,
      "path_hops": 4,
      "e2e_latency_ms": 19.8725136264685,
      "path_bottleneck_count": 0
    },
    {
      "source": 1,
      "target": 5,
      "demand_mbps": 0.6397918000999738,
      "path_hops": 3,
      "e2e_latency_ms": 16.918500202571316,
      "path_bottleneck_count": 0
    },
    {
      "source": 1,
      "target": 6,
      "demand_mbps": 0.7255361357768568,
      "path_hops": 2,
      "e2e_latency_ms": 15.104319013732251,
      "path_bottleneck_count": 0
    },
    {
      "source": 1,
      "target": 7,
      "demand_mbps": 0.30996637639661034,
      "path_hops": 2,
      "e2e_latency_ms": 13.96757611676034,
      "path_bottleneck_count": 0
    },
    {
      "source": 1,
      "target": 8,
      "demand_mbps": 0.2553668662414086,
      "path_hops": 3,
      "e2e_latency_ms": 14.557523574418891,
      "path_bottleneck_count": 0
    },
    {
      "source": 1,
      "target": 9,
      "demand_mbps": 0.8568820305971547,
      "path_hops": 2,
      "e2e_latency_ms": 11.981540377109301,
      "path_bottleneck_count": 0
    },
    {
      "source": 1,
      "target": 10,
      "demand_mbps": 0.5504599799170331,
      "path_hops": 3,
      "e2e_latency_ms": 16.371102272617115,
      "path_bottleneck_count": 0
    },
    {
      "source": 2,
      "target": 0,
      "demand_mbps": 0.8347027504135748,
      "path_hops": 2,
      "e2e_latency_ms": 6.609358426309754,
      "path_bottleneck_count": 0
    },
    {
      "source": 2,
      "target": 1,
      "demand_mbps": 0.8543684236069357,
      "path_hops": 1,
      "e2e_latency_ms": 3.839453069420337,
      "path_bottleneck_count": 0
    },
    {
      "source": 2,
      "target": 3,
      "demand_mbps": 0.6087628458693481,
      "path_hops": 1,
      "e2e_latency_ms": 1.4088531169587555,
      "path_bottleneck_count": 0
    },
    {
      "source": 2,
      "target": 4,
      "demand_mbps": 0.7695794311801624,
      "path_hops": 2,
      "e2e_latency_ms": 20.63734716103129,
      "path_bottleneck_count": 0
    },
    {
      "source": 2,
      "target": 5,
      "demand_mbps": 1.159542647284885,
      "path_hops": 4,
      "e2e_latency_ms": 20.757953271991653,
      "path_bottleneck_count": 0
    },
    {
      "source": 2,
      "target": 6,
      "demand_mbps": 1.239677171665677,
      "path_hops": 3,
      "e2e_latency_ms": 18.943772083152588,
      "path_bottleneck_count": 0
    },
    {
      "source": 2,
      "target": 7,
      "demand_mbps": 1.7061305799064375,
      "path_hops": 3,
      "e2e_latency_ms": 17.807029186180678,
      "path_bottleneck_count": 0
    },
    {
      "source": 2,
      "target": 8,
      "demand_mbps": 0.5094630534625043,
      "path_hops": 2,
      "e2e_latency_ms": 10.718070504998554,
      "path_bottleneck_count": 0
    },
    {
      "source": 2,
      "target": 9,
      "demand_mbps": 0.9564881982659218,
      "path_hops": 1,
      "e2e_latency_ms": 8.142087307688964,
      "path_bottleneck_count": 0
    },
    {
      "source": 2,
      "target": 10,
      "demand_mbps": 2.439247700672962,
      "path_hops": 2,
      "e2e_latency_ms": 12.531649203196778,
      "path_bottleneck_count": 0
    },
    {
      "source": 3,
      "target": 0,
      "demand_mbps": 0.6655381359773305,
      "path_hops": 1,
      "e2e_latency_ms": 3.1869197751507703,
      "path_bottleneck_count": 0
    },
    {
      "source": 3,
      "target": 1,
      "demand_mbps": 0.24210724657753918,
      "path_hops": 2,
      "e2e_latency_ms": 5.956825132040187,
      "path_bottleneck_count": 0
    },
    {
      "source": 3,
      "target": 2,
      "demand_mbps": 0.3055889063302969,
      "path_hops": 1,
      "e2e_latency_ms": 1.4088531169587555,
      "path_bottleneck_count": 0
    },
    {
      "source": 3,
      "target": 4,
      "demand_mbps": 0.656460827193537,
      "path_hops": 4,
      "e2e_latency_ms": 20.289528044729852,
      "path_bottleneck_count": 0
    },
    {
      "source": 3,
      "target": 5,
      "demand_mbps": 0.4704880414686067,
      "path_hops": 3,
      "e2e_latency_ms": 17.33551462083267,
      "path_bottleneck_count": 0
    },
    {
      "source": 3,
      "target": 6,
      "demand_mbps": 0.6085666025667051,
      "path_hops": 2,
      "e2e_latency_ms": 15.521333431993604,
      "path_bottleneck_count": 0
    },
    {
      "source": 3,
      "target": 7,
      "demand_mbps": 0.43366526656361293,
      "path_hops": 2,
      "e2e_latency_ms": 14.384590535021692,
      "path_bottleneck_count": 0
    },
    {
      "source": 3,
      "target": 8,
      "demand_mbps": 0.18996393474312484,
      "path_hops": 3,
      "e2e_latency_ms": 12.12692362195731,
      "path_bottleneck_count": 0
    },
    {
      "source": 3,
      "target": 9,
      "demand_mbps": 0.42597280837265095,
      "path_hops": 2,
      "e2e_latency_ms": 9.55094042464772,
      "path_bottleneck_count": 0
    },
    {
      "source": 3,
      "target": 10,
      "demand_mbps": 1.100305757709766,
      "path_hops": 3,
      "e2e_latency_ms": 13.940502320155534,
      "path_bottleneck_count": 0
    },
    {
      "source": 4,
      "target": 0,
      "demand_mbps": 0.4421621674725615,
      "path_hops": 3,
      "e2e_latency_ms": 17.102608269579083,
      "path_bottleneck_count": 0
    },
    {
      "source": 4,
      "target": 1,
      "demand_mbps": 0.6804609362012656,
      "path_hops": 4,
      "e2e_latency_ms": 19.8725136264685,
      "path_bottleneck_count": 0
    },
    {
      "source": 4,
      "target": 2,
      "demand_mbps": 0.9007408173009396,
      "path_hops": 2,
      "e2e_latency_ms": 20.63734716103129,
      "path_bottleneck_count": 0
    },
    {
      "source": 4,
      "target": 3,
      "demand_mbps": 0.8479111444668628,
      "path_hops": 4,
      "e2e_latency_ms": 20.289528044729852,
      "path_bottleneck_count": 0
    },
    {
      "source": 4,
      "target": 5,
      "demand_mbps": 0.6030582197001418,
      "path_hops": 1,
      "e2e_latency_ms": 2.9540134238971847,
      "path_bottleneck_count": 0
    },
    {
      "source": 4,
      "target": 6,
      "demand_mbps": 0.3041228883188297,
      "path_hops": 2,
      "e2e_latency_ms": 4.76819461273625,
      "path_bottleneck_count": 0
    },
    {
      "source": 4,
      "target": 7,
      "demand_mbps": 0.4600981361130339,
      "path_hops": 1,
      "e2e_latency_ms": 4.5611471169612825,
      "path_bottleneck_count": 0
    },
    {
      "source": 4,
      "target": 8,
      "demand_mbps": 0.24287728353075372,
      "path_hops": 2,
      "e2e_latency_ms": 15.071243050651915,
      "path_bottleneck_count": 0
    },
    {
      "source": 4,
      "target": 9,
      "demand_mbps": 2.3410261288469587,
      "path_hops": 1,
      "e2e_latency_ms": 12.495259853342326,
      "path_bottleneck_count": 0
    },
    {
      "source": 4,
      "target": 10,
      "demand_mbps": 1.0849814953935164,
      "path_hops": 2,
      "e2e_latency_ms": 16.88482174885014,
      "path_bottleneck_count": 0
    },
    {
      "source": 5,
      "target": 0,
      "demand_mbps": 0.907922557204071,
      "path_hops": 2,
      "e2e_latency_ms": 14.148594845681899,
      "path_bottleneck_count": 0
    },
    {
      "source": 5,
      "target": 1,
      "demand_mbps": 1.6299556471524386,
      "path_hops": 3,
      "e2e_latency_ms": 16.918500202571316,
      "path_bottleneck_count": 0
    },
    {
      "source": 5,
      "target": 2,
      "demand_mbps": 1.2544194359029195,
      "path_hops": 4,
      "e2e_latency_ms": 20.757953271991653,
      "path_bottleneck_count": 0
    },
    {
      "source": 5,
      "target": 3,
      "demand_mbps": 0.37909547212442934,
      "path_hops": 3,
      "e2e_latency_ms": 17.33551462083267,
      "path_bottleneck_count": 0
    },
    {
      "source": 5,
      "target": 4,
      "demand_mbps": 0.6060709951659718,
      "path_hops": 1,
      "e2e_latency_ms": 2.9540134238971847,
      "path_bottleneck_count": 0
    },
    {
      "source": 5,
      "target": 6,
      "demand_mbps": 0.7901876511594189,
      "path_hops": 1,
      "e2e_latency_ms": 1.8141811888390647,
      "path_bottleneck_count": 0
    },
    {
      "source": 5,
      "target": 7,
      "demand_mbps": 0.5757774375364003,
      "path_hops": 2,
      "e2e_latency_ms": 5.085292310670559,
      "path_bottleneck_count": 0
    },
    {
      "source": 5,
      "target": 8,
      "demand_mbps": 1.1866293032849493,
      "path_hops": 3,
      "e2e_latency_ms": 18.0252564745491,
      "path_bottleneck_count": 0
    },
    {
      "source": 5,
      "target": 9,
      "demand_mbps": 0.7909395775449559,
      "path_hops": 2,
      "e2e_latency_ms": 15.44927327723951,
      "path_bottleneck_count": 0
    },
    {
      "source": 5,
      "target": 10,
      "demand_mbps": 1.156561883185323,
      "path_hops": 3,
      "e2e_latency_ms": 19.838835172747324,
      "path_bottleneck_count": 0
    },
    {
      "source": 6,
      "target": 0,
      "demand_mbps": 0.44839022670875006,
      "path_hops": 1,
      "e2e_latency_ms": 12.334413656842834,
      "path_bottleneck_count": 0
    },
    {
      "source": 6,
      "target": 1,
      "demand_mbps": 0.40280110288089443,
      "path_hops": 2,
      "e2e_latency_ms": 15.104319013732251,
      "path_bottleneck_count": 0
    },
    {
      "source": 6,
      "target": 2,
      "demand_mbps": 0.25040571820390234,
      "path_hops": 3,
      "e2e_latency_ms": 18.943772083152588,
      "path_bottleneck_count": 0
    },
    {
      "source": 6,
      "target": 3,
      "demand_mbps": 0.5646542724872016,
      "path_hops": 2,
      "e2e_latency_ms": 15.521333431993604,
      "path_bottleneck_count": 0
    },
    {
      "source": 6,
      "target": 4,
      "demand_mbps": 0.4116569971329105,
      "path_hops": 2,
      "e2e_latency_ms": 4.76819461273625,
      "path_bottleneck_count": 0
    },
    {
      "source": 6,
      "target": 5,
      "demand_mbps": 0.8899935694049552,
      "path_hops": 1,
      "e2e_latency_ms": 1.8141811888390647,
      "path_bottleneck_count": 0
    },
    {
      "source": 6,
      "target": 7,
      "demand_mbps": 1.121869010013052,
      "path_hops": 1,
      "e2e_latency_ms": 3.2711111218314946,
      "path_bottleneck_count": 0
    },
    {
      "source": 6,
      "target": 8,
      "demand_mbps": 0.9477440251320648,
      "path_hops": 4,
      "e2e_latency_ms": 19.839437663388164,
      "path_bottleneck_count": 0
    },
    {
      "source": 6,
      "target": 9,
      "demand_mbps": 0.15612363794257375,
      "path_hops": 3,
      "e2e_latency_ms": 17.263454466078574,
      "path_bottleneck_count": 0
    },
    {
      "source": 6,
      "target": 10,
      "demand_mbps": 1.330320031560729,
      "path_hops": 4,
      "e2e_latency_ms": 21.65301636158639,
      "path_bottleneck_count": 0
    },
    {
      "source": 7,
      "target": 0,
      "demand_mbps": 0.24842405866369974,
      "path_hops": 1,
      "e2e_latency_ms": 11.197670759870922,
      "path_bottleneck_count": 0
    },
    {
      "source": 7,
      "target": 1,
      "demand_mbps": 1.1409000530420184,
      "path_hops": 2,
      "e2e_latency_ms": 13.96757611676034,
      "path_bottleneck_count": 0
    },
    {
      "source": 7,
      "target": 2,
      "demand_mbps": 0.8359941148229008,
      "path_hops": 3,
      "e2e_latency_ms": 17.807029186180678,
      "path_bottleneck_count": 0
    },
    {
      "source": 7,
      "target": 3,
      "demand_mbps": 0.7557368087184955,
      "path_hops": 2,
      "e2e_latency_ms": 14.384590535021692,
      "path_bottleneck_count": 0
    },
    {
      "source": 7,
      "target": 4,
      "demand_mbps": 0.7748101949648862,
      "path_hops": 1,
      "e2e_latency_ms": 4.5611471169612825,
      "path_bottleneck_count": 0
    },
    {
      "source": 7,
      "target": 5,
      "demand_mbps": 1.6505705322688247,
      "path_hops": 2,
      "e2e_latency_ms": 5.085292310670559,
      "path_bottleneck_count": 0
    },
    {
      "source": 7,
      "target": 6,
      "demand_mbps": 0.48321224701574345,
      "path_hops": 1,
      "e2e_latency_ms": 3.2711111218314946,
      "path_bottleneck_count": 0
    },
    {
      "source": 7,
      "target": 8,
      "demand_mbps": 0.9960485545328868,
      "path_hops": 3,
      "e2e_latency_ms": 19.6323901676132,
      "path_bottleneck_count": 0
    },
    {
      "source": 7,
      "target": 9,
      "demand_mbps": 1.9715480073897875,
      "path_hops": 2,
      "e2e_latency_ms": 17.05640697030361,
      "path_bottleneck_count": 0
    },
    {
      "source": 7,
      "target": 10,
      "demand_mbps": 0.715992565498047,
      "path_hops": 3,
      "e2e_latency_ms": 21.445968865811423,
      "path_bottleneck_count": 0
    },
    {
      "source": 8,
      "target": 0,
      "demand_mbps": 0.26604959066241274,
      "path_hops": 4,
      "e2e_latency_ms": 17.327428931308308,
      "path_bottleneck_count": 0
    },
    {
      "source": 8,
      "target": 1,
      "demand_mbps": 2.971190499483679,
      "path_hops": 3,
      "e2e_latency_ms": 14.557523574418891,
      "path_bottleneck_count": 0
    },
    {
      "source": 8,
      "target": 2,
      "demand_mbps": 0.8675628857254619,
      "path_hops": 2,
      "e2e_latency_ms": 10.718070504998554,
      "path_bottleneck_count": 0
    },
    {
      "source": 8,
      "target": 3,
      "demand_mbps": 0.5092851326730284,
      "path_hops": 3,
      "e2e_latency_ms": 12.12692362195731,
      "path_bottleneck_count": 0
    },
    {
      "source": 8,
      "target": 4,
      "demand_mbps": 0.30315932066143964,
      "path_hops": 2,
      "e2e_latency_ms": 15.071243050651915,
      "path_bottleneck_count": 0
    },
    {
      "source": 8,
      "target": 5,
      "demand_mbps": 0.4045370388366943,
      "path_hops": 3,
      "e2e_latency_ms": 18.0252564745491,
      "path_bottleneck_count": 0
    },
    {
      "source": 8,
      "target": 6,
      "demand_mbps": 0.9079008300019147,
      "path_hops": 4,
      "e2e_latency_ms": 19.839437663388164,
      "path_bottleneck_count": 0
    },
    {
      "source": 8,
      "target": 7,
      "demand_mbps": 0.49398134320778897,
      "path_hops": 3,
      "e2e_latency_ms": 19.6323901676132,
      "path_bottleneck_count": 0
    },
    {
      "source": 8,
      "target": 9,
      "demand_mbps": 0.3174566536471062,
      "path_hops": 1,
      "e2e_latency_ms": 2.575983197309589,
      "path_bottleneck_count": 0
    },
    {
      "source": 8,
      "target": 10,
      "demand_mbps": 0.6416738366595581,
      "path_hops": 2,
      "e2e_latency_ms": 6.965545092817402,
      "path_bottleneck_count": 0
    },
    {
      "source": 9,
      "target": 0,
      "demand_mbps": 1.3838563776608939,
      "path_hops": 3,
      "e2e_latency_ms": 14.751445733998718,
      "path_bottleneck_count": 0
    },
    {
      "source": 9,
      "target": 1,
      "demand_mbps": 0.4301246253992052,
      "path_hops": 2,
      "e2e_latency_ms": 11.981540377109301,
      "path_bottleneck_count": 0
    },
    {
      "source": 9,
      "target": 2,
      "demand_mbps": 1.033265843078177,
      "path_hops": 1,
      "e2e_latency_ms": 8.142087307688964,
      "path_bottleneck_count": 0
    },
    {
      "source": 9,
      "target": 3,
      "demand_mbps": 0.8641602275056786,
      "path_hops": 2,
      "e2e_latency_ms": 9.55094042464772,
      "path_bottleneck_count": 0
    },
    {
      "source": 9,
      "target": 4,
      "demand_mbps": 0.8428006917510417,
      "path_hops": 1,
      "e2e_latency_ms": 12.495259853342326,
      "path_bottleneck_count": 0
    },
    {
      "source": 9,
      "target": 5,
      "demand_mbps": 2.0765964779747645,
      "path_hops": 2,
      "e2e_latency_ms": 15.44927327723951,
      "path_bottleneck_count": 0
    },
    {
      "source": 9,
      "target": 6,
      "demand_mbps": 1.069021403808947,
      "path_hops": 3,
      "e2e_latency_ms": 17.263454466078574,
      "path_bottleneck_count": 0
    },
    {
      "source": 9,
      "target": 7,
      "demand_mbps": 0.5334528607862173,
      "path_hops": 2,
      "e2e_latency_ms": 17.05640697030361,
      "path_bottleneck_count": 0
    },
    {
      "source": 9,
      "target": 8,
      "demand_mbps": 0.8230707093590723,
      "path_hops": 1,
      "e2e_latency_ms": 2.575983197309589,
      "path_bottleneck_count": 0
    },
    {
      "source": 9,
      "target": 10,
      "demand_mbps": 0.9516359540549572,
      "path_hops": 1,
      "e2e_latency_ms": 4.389561895507813,
      "path_bottleneck_count": 0
    },
    {
      "source": 10,
      "target": 0,
      "demand_mbps": 0.8413944601079056,
      "path_hops": 4,
      "e2e_latency_ms": 19.141007629506532,
      "path_bottleneck_count": 0
    },
    {
      "source": 10,
      "target": 1,
      "demand_mbps": 0.2342623429072505,
      "path_hops": 3,
      "e2e_latency_ms": 16.371102272617115,
      "path_bottleneck_count": 0
    },
    {
      "source": 10,
      "target": 2,
      "demand_mbps": 0.6857711457492491,
      "path_hops": 2,
      "e2e_latency_ms": 12.531649203196778,
      "path_bottleneck_count": 0
    },
    {
      "source": 10,
      "target": 3,
      "demand_mbps": 1.252371770470517,
      "path_hops": 3,
      "e2e_latency_ms": 13.940502320155534,
      "path_bottleneck_count": 0
    },
    {
      "source": 10,
      "target": 4,
      "demand_mbps": 1.527988001433938,
      "path_hops": 2,
      "e2e_latency_ms": 16.88482174885014,
      "path_bottleneck_count": 0
    },
    {
      "source": 10,
      "target": 5,
      "demand_mbps": 1.0032424550887453,
      "path_hops": 3,
      "e2e_latency_ms": 19.838835172747324,
      "path_bottleneck_count": 0
    },
    {
      "source": 10,
      "target": 6,
      "demand_mbps": 1.308651707386068,
      "path_hops": 4,
      "e2e_latency_ms": 21.65301636158639,
      "path_bottleneck_count": 0
    },
    {
      "source": 10,
      "target": 7,
      "demand_mbps": 0.34101007120690713,
      "path_hops": 3,
      "e2e_latency_ms": 21.445968865811423,
      "path_bottleneck_count": 0
    },
    {
      "source": 10,
      "target": 8,
      "demand_mbps": 0.8201031699097215,
      "path_hops": 2,
      "e2e_latency_ms": 6.965545092817402,
      "path_bottleneck_count": 0
    },
    {
      "source": 10,
      "target": 9,
      "demand_mbps": 0.39889356018752026,
      "path_hops": 1,
      "e2e_latency_ms": 4.389561895507813,
      "path_bottleneck_count": 0
    }
  ],
  "summary": {
    "avg_utilization": 0.07760606985104385,
    "max_utilization": 0.31684611531561807
  }
}